<?xml version='1.0' encoding='utf-8'?>
<!--
 FreeCAD Document, see http://www.freecadweb.org for more information...
-->
<Document SchemaVersion="1" FileVersion="2" Split="1" HasExpansion="1">
<Expand  count="6">
  <Expand name="Part" count="2">
    <Expand name="Body" count="2">
      <Expand name="Boolean"/>
      <Expand name="Boolean001"/>
    </Expand>
    <Expand name="Body001"/>
  </Expand>
  <Expand name="CfdAnalysis" count="1">
    <Expand name="Boolean001_Mesh"/>
  </Expand>
  <Expand name="Assembly"/>
  <Expand name="Body002" count="2">
    <Expand name="Origin019"/>
    <Expand name="Revolution"/>
  </Expand>
  <Expand name="Part017" count="1">
    <Expand name="Link030"/>
  </Expand>
  <Expand name="Body003"/>
</Expand>
  <Camera extra="0" id="1" binding="0">
<![CDATA[
OrthographicCamera {
  viewportMapping ADJUST_CAMERA
  position 39.703419 -1.5481625 78.080338
  orientation 0.26105973 0.53991032 -0.80021536  1.3922874
  nearDistance -26.647505
  farDistance 175.58746
  aspectRatio 1
  focalDistance 75.725098
  height 101.5203

}
## overrideMode: As Is]]>
  </Camera>
</Document>
