<?xml version='1.0' encoding='utf-8'?>
<!-- FreeCAD DocumentObject -->
<Document SchemaVersion="4" FileVersion="2">
<Object name="Solid076">
  <Properties Count="8" TransientCount="1">
    <_Property name="_ElementMapVersion" type="App::PropertyString" status="234881024"/>
    <Property name="ColoredElements" type="App::PropertyLinkSubHidden" status="218103808">
      <LinkSub value="" count="0">
      </LinkSub>
    </Property>
    <Property name="ExpressionEngine" type="App::PropertyExpressionEngine" status="67108864">
      <ExpressionEngine count="0"></ExpressionEngine>
    </Property>
    <Property name="Label" type="App::PropertyString" status="134217728">
      <String value="Middle"/>
    </Property>
    <Property name="Label2" type="App::PropertyString" status="128">
      <String value=""/>
    </Property>
    <Property name="Placement" type="App::PropertyPlacement" status="8388608">
      <PropertyPlacement Px="-67.1689417786282" Py="-63.1556406185923" Pz="152.347883907386" Q0="0.7071067811865475" Q1="1.34350288425444e-15" Q2="-1.272792206135785e-15" Q3="0.7071067811865476" A="1.570796326794897" Ox="1" Oy="1.9e-15" Oz="-1.8e-15"/>
    </Property>
    <Property name="Shape" type="Part::PropertyPartShape">
      <Part ElementMap="0.15.70200.4" brep="1">
<![CDATA[

CASCADE Topology V1, (c) Matra-Datavision
Locations 1
1
              1 3.64761178564851e-15 1.1164344944993e-16 -67.1689417786282 
1.11643449449929e-16 2.22044604925031e-16              -1 -63.1556406185923 
-3.64761178564851e-15               1 2.22044604925031e-16 152.347883907386 
Curve2ds 68
1 -3.1415926535897931 7.5 1 0 
1 1.5707963267948966 0 0 1 
1 -3.1415926535897931 0 1 0 
1 2.2355960100410561 0 0 1 
1 2.2355960100410464 0 0 1 
1 1.5707963267948966 0 0 1 
1 3.1415926535897931 7.5 -1 0 
1 0.9059966435487371 0 0 1 
1 0.90599664354874709 0 0 1 
1 3.1415926535897931 0 -1 0 
1 3.1415926535897931 7.5 -1 0 
1 0.66479968324614946 0 0 1 
1 0.66479968324615957 0 0 1 
1 3.1415926535897931 0 -1 0 
1 -3.1415926535897931 7.5 1 0 
1 0 0 0 1 
1 -3.1415926535897931 0 1 0 
1 6.2831853071795862 0 0 1 
1 9.4247779607693793 7.5 -1 0 
1 5.6183856239334267 0 0 1 
1 5.6183856239334364 0 0 1 
1 9.4247779607693793 0 -1 0 
1 3.1415926535897927 7.5 1 0 
1 5.3771886636308395 0 0 1 
1 5.3771886636308492 0 0 1 
1 3.1415926535897927 0 1 0 
1 3.1415926535897931 7.5 1 0 
1 4.7123889803846897 0 0 1 
1 3.1415926535897931 0 1 0 
1 4.7123889803846897 0 0 1 
1 9.4247779607693793 7.5 -1 0 
1 4.0475892971385301 0 0 1 
1 4.0475892971385399 0 0 1 
1 9.4247779607693793 0 -1 0 
1 9.4247779607693793 7.5 -1 0 
1 3.8063923368359425 0 0 1 
1 3.8063923368359527 0 0 1 
1 9.4247779607693793 0 -1 0 
1 3.1415926535897931 7.5 1 0 
1 3.1415926535897931 0 0 1 
1 3.1415926535897931 0 1 0 
1 3.1415926535897931 0 0 1 
1 3.1415926535897931 7.5 -1 0 
1 2.4767929703436335 0 0 1 
1 2.4767929703436438 0 0 1 
1 3.1415926535897931 0 -1 0 
1 9.4247779607693793 0 -1 0 
1 9.4247779607693793 0 0 1 
1 3.1415926535897931 0 0 1 
1 9.4247779607693793 7.5 -1 0 
1 9.4247779607693793 0 -1 0 
1 9.4247779607693793 0 0 1 
1 3.1415926535897931 0 0 1 
1 9.4247779607693793 7.5 -1 0 
1 9.4247779607693793 0 -1 0 
1 9.4247779607693793 0 0 1 
1 3.1415926535897931 0 0 1 
1 9.4247779607693793 7.5 -1 0 
1 9.4247779607693793 0 -1 0 
1 9.4247779607693793 0 0 1 
1 3.1415926535897931 0 0 1 
1 9.4247779607693793 7.5 -1 0 
1 -3.1415926535897931 7.5 1 0 
1 -3.1415926535897931 0 1 0 
1 9.4247779607693793 0 -1 0 
1 9.4247779607693793 0 0 1 
1 3.1415926535897931 0 0 1 
1 9.4247779607693793 7.5 -1 0 
Curves 63
2 13.324999999999999 17 9.5 0 0 -1 1 0 0 0 -1 0 4
1 13.324999999999999 21 17 0 0 -1 
2 13.324999999999999 17 17 0 0 -1 1 0 0 0 -1 0 4
1 15.792605950931598 20.148161506487099 17 0 0 -1 
1 0 21 9.5 -1 0 0 
1 -13.324999999999999 21 17 0 0 -1 
1 0 21 17 -1 0 0 
2 -13.324999999999999 17 9.5 0 0 1 1 0 -0 -0 1 0 4
1 -15.792605950931598 20.148161506487099 17 0 0 -1 
2 -13.324999999999999 17 17 0 0 1 1 0 -0 -0 1 0 4
2 7.2135030206033095e-05 -7.2135030204298304e-05 9.5 0 0 1 1 0 -0 -0 1 0 25.600000000000001
1 -20.148161506487099 15.792605950931598 17 0 0 -1 
2 7.2135030206033095e-05 -7.2135030204298304e-05 17 0 0 1 1 0 -0 -0 1 0 25.600000000000001
2 -17 13.324999999999999 9.5 0 0 -1 1 0 0 0 -1 0 4
1 -21 13.324999999999999 17 0 0 -1 
2 -17 13.324999999999999 17 0 0 -1 1 0 0 0 -1 0 4
1 -21 0 9.5 0 -1 0 
1 -21 -13.324999999999999 17 0 0 -1 
1 -21 0 17 0 -1 0 
2 -17 -13.324999999999999 9.5 0 0 1 1 0 -0 -0 1 0 4
1 -20.148161506487099 -15.792605950931598 17 0 0 -1 
2 -17 -13.324999999999999 17 0 0 1 1 0 -0 -0 1 0 4
2 7.2135030206033095e-05 7.2135030204298304e-05 9.5 0 0 -1 1 0 0 0 -1 0 25.600000000000001
1 -15.792605950931598 -20.148161506487099 17 0 0 -1 
2 7.2135030206033095e-05 7.2135030204298304e-05 17 0 0 -1 1 0 0 0 -1 0 25.600000000000001
2 -13.324999999999999 -17 9.5 0 0 -1 1 0 0 0 -1 0 4
1 -13.324999999999999 -21 17 0 0 -1 
2 -13.324999999999999 -17 17 0 0 -1 1 0 0 0 -1 0 4
1 0 -21 9.5 -1 0 0 
1 13.324999999999999 -21 17 0 0 -1 
1 0 -21 17 -1 0 0 
2 13.324999999999999 -17 9.5 0 0 1 1 0 -0 -0 1 0 4
1 15.792605950931598 -20.148161506487099 17 0 0 -1 
2 13.324999999999999 -17 17 0 0 1 1 0 -0 -0 1 0 4
2 -7.2135030206033095e-05 7.2135030204298304e-05 9.5 0 0 1 1 0 -0 -0 1 0 25.600000000000001
1 20.148161506487099 -15.792605950931598 17 0 0 -1 
2 -7.2135030206033095e-05 7.2135030204298304e-05 17 0 0 1 1 0 -0 -0 1 0 25.600000000000001
2 17 -13.324999999999999 9.5 0 0 -1 1 0 0 0 -1 0 4
1 21 -13.324999999999999 17 0 0 -1 
2 17 -13.324999999999999 17 0 0 -1 1 0 0 0 -1 0 4
1 21 0 9.5 0 -1 0 
1 21 13.324999999999999 17 0 0 -1 
1 21 0 17 0 -1 0 
2 17 13.324999999999999 9.5 0 0 1 1 0 -0 -0 1 0 4
1 20.148161506487099 15.792605950931598 17 0 0 -1 
2 17 13.324999999999999 17 0 0 1 1 0 -0 -0 1 0 4
2 -15.5 -15.5 17 0 0 1 1 0 -0 -0 1 0 1.5
7 0 0  1 2 2  -14 -15.5 17  -14 -15.5 9.5 
 0 2 7.5 2
2 -15.5 -15.5 9.5 0 0 1 1 0 -0 -0 1 0 1.5
2 -15.5 15.5 17 0 0 1 1 0 -0 -0 1 0 1.5
7 0 0  1 2 2  -14 15.5 17  -14 15.5 9.5 
 0 2 7.5 2
2 -15.5 15.5 9.5 0 0 1 1 0 -0 -0 1 0 1.5
2 15.5 15.5 17 0 0 1 1 0 -0 -0 1 0 1.5
7 0 0  1 2 2  17 15.5 17  17 15.5 9.5 
 0 2 7.5 2
2 15.5 15.5 9.5 0 0 1 1 0 -0 -0 1 0 1.5
2 7.2135030386444296e-05 7.2135030388477596e-05 17 0 0 1 1 0 -0 -0 1 0 15.5
7 0 0  1 2 2  15.500072135030386 7.2135030390375803e-05 17  15.500072135030386 7.2135030390375803e-05 9.5 
 0 2 7.5 2
2 7.2135030386444296e-05 7.2135030388477596e-05 9.5 0 0 1 1 0 -0 -0 1 0 15.5
2 -7.2135030206033095e-05 -7.2135030204298304e-05 9.5 0 0 -1 1 0 0 0 -1 0 25.600000000000001
2 -7.2135030206033095e-05 -7.2135030204298304e-05 17 0 0 -1 1 0 0 0 -1 0 25.600000000000001
2 15.5 -15.5 17 0 0 1 1 0 -0 -0 1 0 1.5
7 0 0  1 2 2  17 -15.5 17  17 -15.5 9.5 
 0 2 7.5 2
2 15.5 -15.5 9.5 0 0 1 1 0 -0 -0 1 0 1.5
Polygon3D 0
PolygonOnTriangulations 0
Surfaces 23
2 13.324999999999999 17 17 0 0 -1 -1 0 0 0 1 0 4
1 -0.83835702389478706 0.80681499093771003 9.5 0 0 1 1 0 -0 -0 1 0 
1 0 21 17 0 -1 0 0 0 -1 1 0 0 
1 -0.83835702389478706 0.80681499093771003 17 0 0 1 1 0 -0 -0 1 0 
2 -7.2135030206033095e-05 -7.2135030204298304e-05 17 0 0 -1 -1 0 0 0 1 0 25.600000000000001
2 -13.324999999999999 17 17 0 0 -1 -1 0 0 0 1 0 4
2 7.2135030206033095e-05 -7.2135030204298304e-05 17 0 0 -1 -1 0 0 0 1 0 25.600000000000001
2 -17 13.324999999999999 17 0 0 -1 -1 0 0 0 1 0 4
1 -21 0 17 1 0 0 0 0 -1 -0 1 0 
2 -17 -13.324999999999999 17 0 0 -1 -1 0 0 0 1 0 4
2 7.2135030206033095e-05 7.2135030204298304e-05 17 0 0 -1 -1 0 0 0 1 0 25.600000000000001
2 -13.324999999999999 -17 17 0 0 -1 -1 0 0 0 1 0 4
1 0 -21 17 0 -1 0 0 0 -1 1 0 0 
2 13.324999999999999 -17 17 0 0 -1 -1 0 0 0 1 0 4
2 -7.2135030206033095e-05 7.2135030204298304e-05 17 0 0 -1 -1 0 0 0 1 0 25.600000000000001
2 17 -13.324999999999999 17 0 0 -1 -1 0 0 0 1 0 4
1 21 0 17 1 0 0 0 0 -1 -0 1 0 
2 17 13.324999999999999 17 0 0 -1 -1 0 0 0 1 0 4
10 3.1415926535897931 9.4247779607693793 0 7.5
2 -15.5 -15.5 17 0 0 -1 -1 0 0 0 1 0 1.5
10 3.1415926535897931 9.4247779607693793 0 7.5
2 -15.5 15.5 17 0 0 -1 -1 0 0 0 1 0 1.5
10 3.1415926535897931 9.4247779607693793 0 7.5
2 15.5 15.5 17 0 0 -1 -1 0 0 0 1 0 1.5
10 3.1415926535897931 9.4247779607693793 0 7.5
2 7.2135030386444296e-05 7.2135030388477596e-05 17 0 0 -1 -1 0 0 0 1 0 15.5
10 3.1415926535897931 9.4247779607693793 0 7.5
2 15.5 -15.5 17 0 0 -1 -1 0 0 0 1 0 1.5
Triangulations 0

TShapes 163
Ve
1e-07
13.325 21 9.5
0 0

0101101
*
Ve
1e-07
15.7926059509316 20.1481615064871 9.5
0 0

0101101
*
Ed
 1e-07 1 1 0
1  1 0 4.71238898038469 5.37718866363085
2  1 1 0 4.71238898038469 5.37718866363085
4 C0 1 0 2 0
0

0101000
+163 0 -162 0 *
Ve
1e-07
13.325 21 17
0 0

0101101
*
Ed
 1e-07 1 1 0
1  2 0 0 7.5
2  2 1 0 0 7.5
4 G1 1 0 3 0
0

0101000
+160 0 -163 0 *
Ve
1e-07
15.7926059509316 20.1481615064871 17
0 0

0101101
*
Ed
 1e-07 1 1 0
1  3 0 4.71238898038469 5.37718866363085
2  3 1 0 4.71238898038469 5.37718866363085
4 C0 1 0 4 0
0

0101000
+160 0 -158 0 *
Ed
 1e-07 1 1 0
1  4 0 0 7.5
2  4 1 0 0 7.5
2  5 5 0 0 7.5
4 G1 1 0 5 0
0

0101000
+158 0 -162 0 *
Wi

0101100
-161 0 -159 0 +157 0 +156 0 *
Fa
0  1e-07 1 0

0101000
+155 0 *
Ve
1e-07
-13.325 21 9.5
0 0

0101101
*
Ed
 1e-07 1 1 0
1  5 0 -13.325 13.325
4 C0 3 0 2 0
0

0101000
+163 0 -153 0 *
Ve
1e-07
-13.325 21 17
0 0

0101101
*
Ed
 1e-07 1 1 0
1  6 0 0 7.5
2  6 6 0 0 7.5
4 G1 3 0 6 0
0

0101000
+151 0 -153 0 *
Ed
 1e-07 1 1 0
1  7 0 -13.325 13.325
4 C0 3 0 4 0
0

0101000
+160 0 -151 0 *
Wi

0101100
+152 0 -150 0 -149 0 +159 0 *
Fa
0  1e-07 3 0

0101000
-148 0 *
Ve
1e-07
-15.7926059509316 20.1481615064871 9.5
0 0

0101101
*
Ed
 1e-07 1 1 0
1  8 0 1.5707963267949 2.23559601004106
2  7 6 0 1.5707963267949 2.23559601004106
4 C0 6 0 2 0
0

0101000
+153 0 -146 0 *
Ve
1e-07
-15.7926059509316 20.1481615064871 17
0 0

0101101
*
Ed
 1e-07 1 1 0
1  9 0 0 7.5
2  8 6 0 0 7.5
2  9 7 0 0 7.5
4 G1 6 0 7 0
0

0101000
+144 0 -146 0 *
Ed
 1e-07 1 1 0
1  10 0 1.5707963267949 2.23559601004106
2  10 6 0 1.5707963267949 2.23559601004106
4 C0 6 0 4 0
0

0101000
+151 0 -144 0 *
Wi

0101100
+145 0 -143 0 -142 0 +150 0 *
Fa
0  1e-07 6 0

0101000
+141 0 *
Ve
1e-07
-20.1481615064871 15.7926059509316 9.5
0 0

0101101
*
Ed
 1e-07 1 1 0
1  11 0 2.23559601004105 2.47679297034364
2  11 7 0 2.23559601004105 2.47679297034364
4 C0 7 0 2 0
0

0101000
+146 0 -139 0 *
Ve
1e-07
-20.1481615064871 15.7926059509316 17
0 0

0101101
*
Ed
 1e-07 1 1 0
1  12 0 0 7.5
2  12 7 0 0 7.5
2  13 8 0 0 7.5
4 G1 7 0 8 0
0

0101000
+137 0 -139 0 *
Ed
 1e-07 1 1 0
1  13 0 2.23559601004105 2.47679297034364
2  14 7 0 2.23559601004105 2.47679297034364
4 C0 7 0 4 0
0

0101000
+144 0 -137 0 *
Wi

0101100
+138 0 -136 0 -135 0 +143 0 *
Fa
0  1e-07 7 0

0101000
+134 0 *
Ve
1e-07
-21 13.325 9.5
0 0

0101101
*
Ed
 1e-07 1 1 0
1  14 0 3.14159265358979 3.80639233683595
2  15 8 0 3.14159265358979 3.80639233683595
4 C0 8 0 2 0
0

0101000
+132 0 -139 0 *
Ve
1e-07
-21 13.325 17
0 0

0101101
*
Ed
 1e-07 1 1 0
1  15 0 0 7.5
2  16 8 0 0 7.5
4 G1 8 0 9 0
0

0101000
+130 0 -132 0 *
Ed
 1e-07 1 1 0
1  16 0 3.14159265358979 3.80639233683595
2  17 8 0 3.14159265358979 3.80639233683595
4 C0 8 0 4 0
0

0101000
+130 0 -137 0 *
Wi

0101100
-131 0 -129 0 +128 0 +136 0 *
Fa
0  1e-07 8 0

0101000
+127 0 *
Ve
1e-07
-21 -13.325 9.5
0 0

0101101
*
Ed
 1e-07 1 1 0
1  17 0 -13.325 13.325
4 C0 9 0 2 0
0

0101000
+132 0 -125 0 *
Ve
1e-07
-21 -13.325 17
0 0

0101101
*
Ed
 1e-07 1 1 0
1  18 0 0 7.5
2  18 10 0 0 7.5
4 G1 9 0 10 0
0

0101000
+123 0 -125 0 *
Ed
 1e-07 1 1 0
1  19 0 -13.325 13.325
4 C0 9 0 4 0
0

0101000
+130 0 -123 0 *
Wi

0101100
+124 0 -122 0 -121 0 +129 0 *
Fa
0  1e-07 9 0

0101000
-120 0 *
Ve
1e-07
-20.1481615064871 -15.7926059509316 9.5
0 0

0101101
*
Ed
 1e-07 1 1 0
1  20 0 3.14159265358979 3.80639233683595
2  19 10 0 3.14159265358979 3.80639233683595
4 C0 10 0 2 0
0

0101000
+125 0 -118 0 *
Ve
1e-07
-20.1481615064871 -15.7926059509316 17
0 0

0101101
*
Ed
 1e-07 1 1 0
1  21 0 0 7.5
2  20 10 0 0 7.5
2  21 11 0 0 7.5
4 G1 10 0 11 0
0

0101000
+116 0 -118 0 *
Ed
 1e-07 1 1 0
1  22 0 3.14159265358979 3.80639233683595
2  22 10 0 3.14159265358979 3.80639233683595
4 C0 10 0 4 0
0

0101000
+123 0 -116 0 *
Wi

0101100
+117 0 -115 0 -114 0 +122 0 *
Fa
0  1e-07 10 0

0101000
+113 0 *
Ve
1e-07
-15.7926059509316 -20.1481615064871 9.5
0 0

0101101
*
Ed
 1e-07 1 1 0
1  23 0 2.23559601004105 2.47679297034364
2  23 11 0 2.23559601004105 2.47679297034364
4 C0 11 0 2 0
0

0101000
+111 0 -118 0 *
Ve
1e-07
-15.7926059509316 -20.1481615064871 17
0 0

0101101
*
Ed
 1e-07 1 1 0
1  24 0 0 7.5
2  24 11 0 0 7.5
2  25 12 0 0 7.5
4 G1 11 0 12 0
0

0101000
+109 0 -111 0 *
Ed
 1e-07 1 1 0
1  25 0 2.23559601004105 2.47679297034364
2  26 11 0 2.23559601004105 2.47679297034364
4 C0 11 0 4 0
0

0101000
+109 0 -116 0 *
Wi

0101100
-110 0 -108 0 +107 0 +115 0 *
Fa
0  1e-07 11 0

0101000
+106 0 *
Ve
1e-07
-13.325 -21 9.5
0 0

0101101
*
Ed
 1e-07 1 1 0
1  26 0 1.5707963267949 2.23559601004106
2  27 12 0 1.5707963267949 2.23559601004106
4 C0 12 0 2 0
0

0101000
+104 0 -111 0 *
Ve
1e-07
-13.325 -21 17
0 0

0101101
*
Ed
 1e-07 1 1 0
1  27 0 0 7.5
2  28 12 0 0 7.5
4 G1 12 0 13 0
0

0101000
+102 0 -104 0 *
Ed
 1e-07 1 1 0
1  28 0 1.5707963267949 2.23559601004106
2  29 12 0 1.5707963267949 2.23559601004106
4 C0 12 0 4 0
0

0101000
+102 0 -109 0 *
Wi

0101100
-103 0 -101 0 +100 0 +108 0 *
Fa
0  1e-07 12 0

0101000
+99 0 *
Ve
1e-07
13.325 -21 9.5
0 0

0101101
*
Ed
 1e-07 1 1 0
1  29 0 -13.325 13.325
4 C0 13 0 2 0
0

0101000
+97 0 -104 0 *
Ve
1e-07
13.325 -21 17
0 0

0101101
*
Ed
 1e-07 1 1 0
1  30 0 0 7.5
2  30 14 0 0 7.5
4 G1 13 0 14 0
0

0101000
+95 0 -97 0 *
Ed
 1e-07 1 1 0
1  31 0 -13.325 13.325
4 C0 13 0 4 0
0

0101000
+95 0 -102 0 *
Wi

0101100
-96 0 -94 0 +93 0 +101 0 *
Fa
0  1e-07 13 0

0101000
+92 0 *
Ve
1e-07
15.7926059509316 -20.1481615064871 9.5
0 0

0101101
*
Ed
 1e-07 1 1 0
1  32 0 4.71238898038469 5.37718866363085
2  31 14 0 4.71238898038469 5.37718866363085
4 C0 14 0 2 0
0

0101000
+97 0 -90 0 *
Ve
1e-07
15.7926059509316 -20.1481615064871 17
0 0

0101101
*
Ed
 1e-07 1 1 0
1  33 0 0 7.5
2  32 14 0 0 7.5
2  33 15 0 0 7.5
4 G1 14 0 15 0
0

0101000
+88 0 -90 0 *
Ed
 1e-07 1 1 0
1  34 0 4.71238898038469 5.37718866363085
2  34 14 0 4.71238898038469 5.37718866363085
4 C0 14 0 4 0
0

0101000
+95 0 -88 0 *
Wi

0101100
+89 0 -87 0 -86 0 +94 0 *
Fa
0  1e-07 14 0

0101000
+85 0 *
Ve
1e-07
20.1481615064871 -15.7926059509316 9.5
0 0

0101101
*
Ed
 1e-07 1 1 0
1  35 0 5.37718866363084 5.61838562393344
2  35 15 0 5.37718866363084 5.61838562393344
4 C0 15 0 2 0
0

0101000
+90 0 -83 0 *
Ve
1e-07
20.1481615064871 -15.7926059509316 17
0 0

0101101
*
Ed
 1e-07 1 1 0
1  36 0 0 7.5
2  36 15 0 0 7.5
2  37 16 0 0 7.5
4 G1 15 0 16 0
0

0101000
+81 0 -83 0 *
Ed
 1e-07 1 1 0
1  37 0 5.37718866363084 5.61838562393344
2  38 15 0 5.37718866363084 5.61838562393344
4 C0 15 0 4 0
0

0101000
+88 0 -81 0 *
Wi

0101100
+82 0 -80 0 -79 0 +87 0 *
Fa
0  1e-07 15 0

0101000
+78 0 *
Ve
1e-07
21 -13.325 9.5
0 0

0101101
*
Ed
 1e-07 1 1 0
1  38 0 0 0.66479968324616
2  39 16 0 0 0.66479968324616
4 C0 16 0 2 0
0

0101000
+76 0 -83 0 *
Ve
1e-07
21 -13.325 17
0 0

0101101
*
Ed
 1e-07 1 1 0
1  39 0 0 7.5
2  40 16 0 0 7.5
4 G1 16 0 17 0
0

0101000
+74 0 -76 0 *
Ed
 1e-07 1 1 0
1  40 0 0 0.66479968324616
2  41 16 0 0 0.66479968324616
4 C0 16 0 4 0
0

0101000
+74 0 -81 0 *
Wi

0101100
-75 0 -73 0 +72 0 +80 0 *
Fa
0  1e-07 16 0

0101000
+71 0 *
Ve
1e-07
21 13.325 9.5
0 0

0101101
*
Ed
 1e-07 1 1 0
1  41 0 -13.325 13.325
4 C0 17 0 2 0
0

0101000
+69 0 -76 0 *
Ve
1e-07
21 13.325 17
0 0

0101101
*
Ed
 1e-07 1 1 0
1  42 0 0 7.5
2  42 18 0 0 7.5
4 G1 17 0 18 0
0

0101000
+67 0 -69 0 *
Ed
 1e-07 1 1 0
1  43 0 -13.325 13.325
4 C0 17 0 4 0
0

0101000
+67 0 -74 0 *
Wi

0101100
-68 0 -66 0 +65 0 +73 0 *
Fa
0  1e-07 17 0

0101000
+64 0 *
Ve
1e-07
20.1481615064871 15.7926059509316 9.5
0 0

0101101
*
Ed
 1e-07 1 1 0
1  44 0 0 0.66479968324616
2  43 18 0 0 0.66479968324616
4 C0 18 0 2 0
0

0101000
+69 0 -62 0 *
Ve
1e-07
20.1481615064871 15.7926059509316 17
0 0

0101101
*
Ed
 1e-07 1 1 0
1  45 0 0 7.5
2  44 18 0 0 7.5
2  45 5 0 0 7.5
4 G1 18 0 5 0
0

0101000
+60 0 -62 0 *
Ed
 1e-07 1 1 0
1  46 0 0 0.66479968324616
2  46 18 0 0 0.66479968324616
4 C0 18 0 4 0
0

0101000
+67 0 -60 0 *
Wi

0101100
+61 0 -59 0 -58 0 +66 0 *
Fa
0  1e-07 18 0

0101000
+57 0 *
Ve
1e-05
-14 -15.5 17
0 0

0101101
*
Ed
 1e-07 1 1 0
1  47 0 0 6.28318530717959
2  47 19 0 0 6.28318530717959
4 C0 19 0 4 0
0

0101000
-55 0 +55 0 *
Ve
1e-05
-14 -15.5 9.5
0 0

0101101
*
Ed
 1e-05 1 1 0
1  48 0 0 7.5
3  48 49CN 19 0 0 7.5
0

0101000
+55 0 -53 0 *
Ed
 1e-07 1 1 0
1  49 0 0 6.28318530717959
2  50 19 0 0 6.28318530717959
4 C0 19 0 2 0
0

0101000
+53 0 -53 0 *
Wi

0101100
-54 0 +52 0 +51 0 -52 0 *
Fa
0  1e-07 19 0

0101000
+50 0 *
Ve
1e-05
-14 15.5 17
0 0

0101101
*
Ed
 1e-07 1 1 0
1  50 0 0 6.28318530717959
2  51 20 0 0 6.28318530717959
4 C0 20 0 4 0
0

0101000
-48 0 +48 0 *
Ve
1e-05
-14 15.5 9.5
0 0

0101101
*
Ed
 1e-05 1 1 0
1  51 0 0 7.5
3  52 53CN 20 0 0 7.5
0

0101000
+48 0 -46 0 *
Ed
 1e-07 1 1 0
1  52 0 0 6.28318530717959
2  54 20 0 0 6.28318530717959
4 C0 20 0 2 0
0

0101000
+46 0 -46 0 *
Wi

0101100
-47 0 +45 0 +44 0 -45 0 *
Fa
0  1e-07 20 0

0101000
+43 0 *
Ve
1e-05
17 15.5 17
0 0

0101101
*
Ed
 1e-07 1 1 0
1  53 0 0 6.28318530717959
2  55 21 0 0 6.28318530717959
4 C0 21 0 4 0
0

0101000
-41 0 +41 0 *
Ve
1e-05
17 15.5 9.5
0 0

0101101
*
Ed
 1e-05 1 1 0
1  54 0 0 7.5
3  56 57CN 21 0 0 7.5
0

0101000
+41 0 -39 0 *
Ed
 1e-07 1 1 0
1  55 0 0 6.28318530717959
2  58 21 0 0 6.28318530717959
4 C0 21 0 2 0
0

0101000
+39 0 -39 0 *
Wi

0101100
-40 0 +38 0 +37 0 -38 0 *
Fa
0  1e-07 21 0

0101000
+36 0 *
Ve
1e-05
15.5000721350304 7.21350303884776e-05 17
0 0

0101101
*
Ed
 1e-07 1 1 0
1  56 0 0 6.28318530717959
2  59 22 0 0 6.28318530717959
4 C0 22 0 4 0
0

0101000
-34 0 +34 0 *
Ve
1e-05
15.5000721350304 7.21350303884776e-05 9.5
0 0

0101101
*
Ed
 1e-05 1 1 0
1  57 0 0 7.5
3  60 61CN 22 0 0 7.5
0

0101000
+34 0 -32 0 *
Ed
 1e-07 1 1 0
1  58 0 0 6.28318530717959
2  62 22 0 0 6.28318530717959
4 C0 22 0 2 0
0

0101000
+32 0 -32 0 *
Wi

0101100
-33 0 +31 0 +30 0 -31 0 *
Fa
0  1e-07 22 0

0101000
+29 0 *
Ed
 1e-07 1 1 0
1  59 0 5.37718866363084 5.61838562393344
2  63 5 0 5.37718866363084 5.61838562393344
4 C0 5 0 2 0
0

0101000
+162 0 -62 0 *
Ed
 1e-07 1 1 0
1  60 0 5.37718866363084 5.61838562393344
2  64 5 0 5.37718866363084 5.61838562393344
4 C0 5 0 4 0
0

0101000
+158 0 -60 0 *
Wi

0101100
-27 0 -156 0 +26 0 +59 0 *
Fa
0  1e-07 5 0

0101000
+25 0 *
Ve
1e-05
17 -15.5 17
0 0

0101101
*
Ed
 1e-07 1 1 0
1  61 0 0 6.28318530717959
2  65 23 0 0 6.28318530717959
4 C0 23 0 4 0
0

0101000
-23 0 +23 0 *
Ve
1e-05
17 -15.5 9.5
0 0

0101101
*
Ed
 1e-05 1 1 0
1  62 0 0 7.5
3  66 67CN 23 0 0 7.5
0

0101000
+23 0 -21 0 *
Ed
 1e-07 1 1 0
1  63 0 0 6.28318530717959
2  68 23 0 0 6.28318530717959
4 C0 23 0 2 0
0

0101000
+21 0 -21 0 *
Wi

0101100
-22 0 +20 0 +19 0 -20 0 *
Fa
0  1e-07 23 0

0101000
+18 0 *
Wi

0101100
-157 0 +149 0 +142 0 +135 0 -128 0 +121 0 +114 0 -107 0 -100 0 -93 0 
+86 0 +79 0 -72 0 -65 0 +58 0 -26 0 *
Wi

0101100
-33 0 *
Wi

0101100
-40 0 *
Wi

0101100
-47 0 *
Wi

0101100
-54 0 *
Wi

0101100
-22 0 *
Fa
0  1e-07 4 0

0101000
+16 0 +15 0 +14 0 +13 0 +12 0 +11 0 *
Wi

0101100
+161 0 +27 0 -61 0 +68 0 +75 0 -82 0 -89 0 +96 0 +103 0 +110 0 
-117 0 -124 0 +131 0 -138 0 -145 0 -152 0 *
Wi

0101100
+30 0 *
Wi

0101100
+37 0 *
Wi

0101100
+44 0 *
Wi

0101100
+51 0 *
Wi

0101100
+19 0 *
Fa
0  1e-07 2 0

0101000
-9 0 -8 0 -7 0 -6 0 -5 0 -4 0 *
Sh

0101100
+154 0 -147 0 +140 0 +133 0 +126 0 -119 0 +112 0 +105 0 +98 0 +91 0 
+84 0 +77 0 +70 0 +63 0 +56 0 -49 0 -42 0 -35 0 -28 0 +24 0 
-17 0 +10 0 -3 0 *
So

0100000
+2 0 *

+1 1 ]]>
      </Part>
      <ElementMap/>
    </Property>
    <Property name="TreeRank" type="App::PropertyInteger" status="2184">
      <Integer value="838"/>
    </Property>
    <Property name="Visibility" type="App::PropertyBool" status="648">
      <Bool value="true"/>
    </Property>
  </Properties>
</Object>
</Document>
